picture_comparator_muri/__init__.py
picture_comparator_muri/main.py
picture_comparator_muri/utils.py
picture_comparator_muri/controller/__init__.py
picture_comparator_muri/controller/action_buttons.py
picture_comparator_muri/controller/application.py
picture_comparator_muri/controller/comparator.py
picture_comparator_muri/controller/directory_picker.py
picture_comparator_muri/controller/group_list.py
picture_comparator_muri/controller/log.py
picture_comparator_muri/controller/main_window.py
picture_comparator_muri/controller/matches.py
picture_comparator_muri/controller/settings.py
picture_comparator_muri/model/__init__.py
picture_comparator_muri/model/display_settings.py
picture_comparator_muri/model/exceptions.py
picture_comparator_muri/model/file.py
picture_comparator_muri/model/group_selection_model.py
picture_comparator_muri/model/image_group.py
picture_comparator_muri/model/image_info.py
picture_comparator_muri/model/log_engine.py
picture_comparator_muri/model/renamer_model.py
picture_comparator_muri/model/search_engine.py
picture_comparator_muri/model/utils.py
picture_comparator_muri/model/watched_list.py
picture_comparator_muri/resources/__init__.py
picture_comparator_muri/resources/edit-delete.svg
picture_comparator_muri/resources/resources.py
picture_comparator_muri/view/__init__.py
picture_comparator_muri/view/comparator_view.py
picture_comparator_muri/view/directory_picker.py
picture_comparator_muri/view/directory_picker_ui.py
picture_comparator_muri/view/group_list_view.py
picture_comparator_muri/view/log.py
picture_comparator_muri/view/log_ui.py
picture_comparator_muri/view/main_window.py
picture_comparator_muri/view/main_window_ui.py
picture_comparator_muri/view/manual_rename_ui.py
picture_comparator_muri/view/matches_view.py
picture_comparator_muri/view/renamer_dialog.py
picture_comparator_muri/view/renamer_file_tree_view.py
picture_comparator_muri/view/renamer_ui.py
picture_comparator_muri-0.1.16.dist-info/METADATA
picture_comparator_muri-0.1.16.dist-info/WHEEL
picture_comparator_muri-0.1.16.dist-info/entry_points.txt
picture_comparator_muri-0.1.16.dist-info/licenses/LICENSE
picture_comparator_muri-0.1.16.dist-info/RECORD
