Metadata-Version: 2.1
Name: picture-comparator-muri
Version: 0.1.16
Summary: Finds similar images in chosen directory.
Project-URL: Homepage, https://gitlab.com/muria/picture-comparator
Project-URL: Bug Tracker, https://gitlab.com/muria/picture-comparator/-/issues
Author-email: Muri <gurtos29A@gmail.com>
License-Expression: GPL-3.0-or-later
License-File: LICENSE
Classifier: License :: OSI Approved :: GNU General Public License v3 (GPLv3)
Classifier: Operating System :: POSIX
Classifier: Programming Language :: Python :: 3
Requires-Python: >=3.7
Requires-Dist: imagehash~=4.2.1
Requires-Dist: pyside6==6.2.2.1
Requires-Dist: python-magic~=0.4.24
Requires-Dist: scikit-learn~=1.0.2
Requires-Dist: wand~=0.6.7
